docs/__init__.py
pyjsonfeed/__init__.py
pyjsonfeed/pyjsonfeed.py
pyjsonfeed-1.0.0.dist-info/METADATA
pyjsonfeed-1.0.0.dist-info/RECORD
pyjsonfeed-1.0.0.dist-info/WHEEL
pyjsonfeed-1.0.0.dist-info/top_level.txt
tests/__init__.py
tests/tests.py
