Metadata-Version: 2.1
Name: pyjsonfeed
Version: 1.0.0
Summary: A package for JSON feeds inspired by feedparser.
Home-page: https://github.com/noaoh/pyjsonfeed
Author: noaoh
Author-email: noahryanholt@gmail.com
License: MIT
Platform: UNKNOWN
Requires-Python: >=3.4
